Maverick/Builder.py
Maverick/Cache.py
Maverick/Config.py
Maverick/Content.py
Maverick/Markdown.py
Maverick/Metadata.py
Maverick/Router.py
Maverick/Template.py
Maverick/Utils.py
Maverick/__init__.py
Maverick/mistune_plugins/__init__.py
Maverick/mistune_plugins/autotag.py
Maverick/mistune_plugins/blockcode.py
Maverick/mistune_plugins/blockmath.py
Maverick/mistune_plugins/image.py
Maverick/mistune_plugins/inline_footnote.py
Maverick/mistune_plugins/linkcard.py
Maverick/mistune_plugins/paragraph.py
Maverick/mistune_plugins/ruby.py
mvrk-1.2.1.data/scripts/mvrk.py
mvrk-1.2.1.dist-info/LICENSE
mvrk-1.2.1.dist-info/METADATA
mvrk-1.2.1.dist-info/WHEEL
mvrk-1.2.1.dist-info/top_level.txt
mvrk-1.2.1.dist-info/RECORD
