Metadata-Version: 2.1
Name: mvrk
Version: 1.2.1
Summary: 🏄‍ A static blog generator built with Python.
Home-page: https://github.com/AlanDecode/Maverick
Author: AlanDecode
Author-email: zytbuaa1415@gmail.com
License: MIT
Platform: UNKNOWN
Classifier: License :: OSI Approved :: MIT License
Classifier: Programming Language :: Python
Classifier: Programming Language :: Python :: 3
Classifier: Programming Language :: Python :: 3.5
Classifier: Programming Language :: Python :: Implementation :: CPython
Classifier: Programming Language :: Python :: Implementation :: PyPy
Requires-Python: >=3.5.0
Requires-Dist: Jinja2
Requires-Dist: moment
Requires-Dist: mistune (==2.0.0a4)
Requires-Dist: pygments
Requires-Dist: Pillow
Requires-Dist: feedgen
Requires-Dist: pyyaml
Requires-Dist: chardet
Requires-Dist: flake8
Requires-Dist: yapf
